horizon_fastapi_template/__init__.py
horizon_fastapi_template/utils.py
horizon_fastapi_template/_internal/__init__.py
horizon_fastapi_template/_internal/database/__init__.py
horizon_fastapi_template/_internal/database/basic_api.py
horizon_fastapi_template/_internal/database/ftp_client.py
horizon_fastapi_template/_internal/database/kube_client.py
horizon_fastapi_template/_internal/middlewares/__init__.py
horizon_fastapi_template/_internal/middlewares/exception.py
horizon_fastapi_template/_internal/middlewares/log_request.py
horizon_fastapi_template/_internal/middlewares/time_request.py
horizon_fastapi_template/_internal/models/__init__.py
horizon_fastapi_template/_internal/models/graphql.py
horizon_fastapi_template/_internal/models/handler.py
horizon_fastapi_template/_internal/routes/__init__.py
horizon_fastapi_template/_internal/routes/metrics.py
horizon_fastapi_template/_internal/routes/probes.py
horizon_fastapi_template/_internal/routes/qraphql.py
horizon_fastapi_template/_internal/routes/swagger.py
horizon_fastapi_template/_internal/tasks/__init__.py
horizon_fastapi_template/_internal/tasks/uptime.py
horizon_fastapi_template/_internal/utils/__init__.py
horizon_fastapi_template/_internal/utils/config.py
horizon_fastapi_template/_internal/utils/logger.py
horizon_fastapi_template/static/graphiql/index.html
horizon_fastapi_template/static/graphiql/static/css/graphiql.min.css
horizon_fastapi_template/static/graphiql/static/css/style.css
horizon_fastapi_template/static/graphiql/static/js/graphiql.min.js
horizon_fastapi_template/static/graphiql/static/js/index.umd.js
horizon_fastapi_template/static/graphiql/static/js/js.cookie.min.js
horizon_fastapi_template/static/graphiql/static/js/react-dom.production.min.js
horizon_fastapi_template/static/graphiql/static/js/react.production.min.js
horizon_fastapi_template/static/swagger/favicon.ico
horizon_fastapi_template/static/swagger/redoc.standalone.js
horizon_fastapi_template/static/swagger/swagger-ui-bundle.js
horizon_fastapi_template-0.0.5.dev1.dist-info/licenses/LICENSE
horizon_fastapi_template-0.0.5.dev1.dist-info/METADATA
horizon_fastapi_template-0.0.5.dev1.dist-info/WHEEL
horizon_fastapi_template-0.0.5.dev1.dist-info/top_level.txt
horizon_fastapi_template-0.0.5.dev1.dist-info/RECORD
