Metadata-Version: 2.4
Name: horizon-fastapi-template
Version: 0.0.5.dev1
Summary: A reusable FastAPI application factory
Author: Chaim Mendelson and Yehonatan Magen
License:                                  Apache License
Requires-Python: >=3.9
License-File: LICENSE
Requires-Dist: aioftp>=0.21
Requires-Dist: fastapi>=0.110
Requires-Dist: httpx>=0.24
Requires-Dist: kubernetes-asyncio>=29.0
Requires-Dist: loguru>=0.7
Requires-Dist: prometheus-client>=0.17
Requires-Dist: pydantic>=2.11.10
Requires-Dist: pydantic-settings>=2.0
Requires-Dist: strawberry-graphql[fastapi]>=0.118.0
Requires-Dist: uvicorn>=0.24
Requires-Dist: pytest>=7.4
Requires-Dist: pytest-asyncio>=0.22
Requires-Dist: respx>=0.18.0
Dynamic: license-file
